mypackage/StateFa.py
mypackage/__init__.py
mypackage/dfa.py
mypackage/fa.py
mypackage/fa_interface.py
mypackage/nfa.py
Finit_Automaton-0.1.dist-info/LICENSE.md
Finit_Automaton-0.1.dist-info/METADATA
Finit_Automaton-0.1.dist-info/WHEEL
Finit_Automaton-0.1.dist-info/top_level.txt
Finit_Automaton-0.1.dist-info/RECORD
