Metadata-Version: 2.1
Name: Finit-Automaton
Version: 0.1
Summary: Operations for finit automaton
Home-page: https://github.com/manudiv16/Finit-Automaton
Author: manu
Author-email: manudiv16@gmail.com
License: MIT License
Platform: UNKNOWN
